odoo9_addon_l10n_es_dua-9.0.1.0.0-py2.7-nspkg.pth
odoo9_addon_l10n_es_dua-9.0.1.0.0.dist-info/DESCRIPTION.rst
odoo9_addon_l10n_es_dua-9.0.1.0.0.dist-info/METADATA
odoo9_addon_l10n_es_dua-9.0.1.0.0.dist-info/RECORD
odoo9_addon_l10n_es_dua-9.0.1.0.0.dist-info/WHEEL
odoo9_addon_l10n_es_dua-9.0.1.0.0.dist-info/metadata.json
odoo9_addon_l10n_es_dua-9.0.1.0.0.dist-info/namespace_packages.txt
odoo9_addon_l10n_es_dua-9.0.1.0.0.dist-info/top_level.txt
odoo_addons/l10n_es_dua/README.rst
odoo_addons/l10n_es_dua/__init__.py
odoo_addons/l10n_es_dua/__openerp__.py
odoo_addons/l10n_es_dua/data/fiscal_position_taxes_dua.xml
odoo_addons/l10n_es_dua/data/fiscal_positions_dua.xml
odoo_addons/l10n_es_dua/data/products_dua.xml
odoo_addons/l10n_es_dua/data/taxes_dua.xml
odoo_addons/l10n_es_dua/static/description/icon.png
